praatio/__init__.py
praatio/audio.py
praatio/data_points.py
praatio/klattgrid.py
praatio/pitch_and_intensity.py
praatio/praat_scripts.py
praatio/praatio_scripts.py
praatio/textgrid.py
praatio/tgio.py
praatio/data_classes/__init__.py
praatio/data_classes/data_point.py
praatio/data_classes/interval_tier.py
praatio/data_classes/klattgrid.py
praatio/data_classes/point_tier.py
praatio/data_classes/textgrid.py
praatio/data_classes/textgrid_tier.py
praatio/praatScripts/annotate_silences.praat
praatio/praatScripts/change_gender.praat
praatio/praatScripts/change_intensity.praat
praatio/praatScripts/get_formants.praat
praatio/praatScripts/get_intensity.praat
praatio/praatScripts/get_pitch.praat
praatio/praatScripts/get_pitch_and_intensity.praat
praatio/praatScripts/get_pitch_and_intensity_segments.praat
praatio/praatScripts/get_pitchtier.praat
praatio/praatScripts/get_pulses.praat
praatio/praatScripts/get_spectral_info.praat
praatio/praatScripts/resynthesize_duration.praat
praatio/praatScripts/resynthesize_from_klattgrid.praat
praatio/praatScripts/resynthesize_pitch.praat
praatio/praatScripts/sound_to_klattgrid.praat
praatio/utilities/__init__.py
praatio/utilities/constants.py
praatio/utilities/errors.py
praatio/utilities/my_math.py
praatio/utilities/textgrid_io.py
praatio/utilities/timit.py
praatio/utilities/utils.py
praatio-6.2.1.dist-info/LICENSE
praatio-6.2.1.dist-info/METADATA
praatio-6.2.1.dist-info/WHEEL
praatio-6.2.1.dist-info/top_level.txt
praatio-6.2.1.dist-info/RECORD
