Metadata-Version: 2.1
Name: praatio
Version: 6.2.1
Summary: A library for working with praat, textgrids, time aligned audio transcripts, and audio files.
Home-page: https://github.com/timmahrt/praatIO
Author: Tim Mahrt
Author-email: timmahrt@gmail.com
License: LICENSE
Requires-Python: >3.6.0
License-File: LICENSE
Requires-Dist: typing-extensions
